stastar/__init__.py
stastar/grid.py
stastar/neighbour_table.py
stastar/planner.py
stastar/state.py
space_time_astar-0.8.dist-info/LICENSE.txt 
space_time_astar-0.8.dist-info/METADATA
space_time_astar-0.8.dist-info/WHEEL
space_time_astar-0.8.dist-info/top_level.txt
space_time_astar-0.8.dist-info/RECORD
