Metadata-Version: 2.1
Name: space-time-astar
Version: 0.8
Summary: A* search algorithm with an added time dimension to deal with dynamic obstacles.
Home-page: https://github.com/GavinPHR/Space-Time-AStar
Author: Haoran Peng
Author-email: gavinsweden@gmail.com
License: MIT
Keywords: astar-algorithm,obstacle-avoidance,time-dimension
Platform: UNKNOWN
Classifier: Development Status :: 4 - Beta
Classifier: Intended Audience :: Developers
Classifier: Topic :: Software Development :: Build Tools
Classifier: License :: OSI Approved :: MIT License
Requires-Python: >=3.5
Requires-Dist: numpy
Requires-Dist: scipy
